{
  "common": {
    "lastUpdated": "最后更新：",
    "contactEmail": "son.jaehoon0826@gmail.com",
    "contactLabel": "电子邮件：",
    "weAreHereToHelp": "我们随时为您提供帮助"
  },
  "landing": {
    "hero": {
      "appName": "Lobe",
      "headline": "为您量身定制的大脑训练",
      "cta": "立即下载"
    },
    "howItWorks": {
      "title": "工作原理",
      "subtitle": "Lobe 通过科学支持的大脑游戏增强您的思维能力。"
    },
    "gamesShowcase": {
      "title": "通过益智游戏\n保持敏锐",
      "description": "解决旨在提高解决问题能力和增强创造力的每日谜题。从记忆挑战到语言游戏，以您的方式训练大脑。",
      "cta": "开始训练",
      "games": {
        "wordGame": "文字游戏",
        "memoryMatrix": "记忆矩阵",
        "stroopClash": "斯特鲁普冲突"
      }
    }
  },
  "footer": {
    "appName": "Lobe",
    "builtBy": "构建者 ",
    "links": {
      "home": "首页",
      "terms": "条款",
      "privacy": "隐私",
      "eula": "最终用户许可协议"
    }
  },
  "support": {
    "title": "支持",
    "intro": "欢迎使用 Lobe 支持。如果您有任何问题、需要帮助或想要报告问题，这里就是正确的地方。",
    "contact": {
      "title": "联系我们",
      "description": "如有任何支持咨询，请通过电子邮件联系我们要：",
      "responseTime": "我们的目标是在 24-48 小时内回复所有咨询。"
    },
    "faq": {
      "title": "常见问题解答",
      "items": [
        {
          "question": "如何开始使用 Lobe？",
          "answer": "首次打开 Lobe 时，您将通过一个简单的入职流程。这将帮助您设置个人资料并向您介绍应用程序的功能。只需按照屏幕上的说明即可开始。"
        },
        {
          "question": "如何删除我的帐户？",
          "answer": "您可以通过两种方式删除帐户：",
          "list": [
            "从应用程序：导航到您的个人资料设置并选择删除帐户的选项。",
            "联系我们：发送请求删除帐户的电子邮件。请包含与您的帐户关联的电子邮件地址。"
          ]
        },
        {
          "question": "如何报告错误或问题？",
          "answer": "如果您遇到错误或在使用应用程序时遇到问题，请给我们发送电子邮件，说明问题描述、您使用的设备以及重现问题的任何步骤。截图也会很有帮助。"
        },
        {
          "question": "如何管理我的订阅？",
          "answer": "订阅通过 App Store 管理。要查看、修改或取消您的订阅：",
          "list": [
            "打开设备上的“设置”应用",
            "点击顶部的您的姓名",
            "点击“订阅”",
            "选择 Lobe 以管理您的订阅"
          ]
        }
      ]
    },
    "resources": {
      "title": "其他资源",
      "items": [
        {
          "label": "隐私政策",
          "desc": " – 了解我们要如何处理您的数据",
          "href": "/privacy"
        },
        {
          "label": "使用条款",
          "desc": " – 查看我们的条款和条件",
          "href": "/terms"
        },
        {
          "label": "最终用户许可协议",
          "desc": " – 阅读我们的 EULA",
          "href": "/eula"
        }
      ]
    },
    "feedback": {
      "title": "反馈",
      "description": "我们要重视您的反馈！如果您有改进 Lobe 的建议或新功能的想法，我们要很乐意听取您的意见。请将您的想法发送至 "
    }
  },
  "legal": {
    "eula": {
      "title": "最终用户许可协议",
      "lastUpdated": "2026年1月8日",
      "intro": [
        "本最终用户许可协议 (“EULA”) 是您 (“用户”) 与位于美国特拉华州的个人 Lobe 运营者 (“许可方”、“我们”或“我们的”) 之间关于您使用 Lobe 移动应用程序 (“App”) 的法律协议。",
        "下载、安装或使用本应用程序，即表示您同意受本 EULA 的约束。如果您不同意，请勿使用本应用程序。"
      ],
      "sections": [
        {
          "title": "1. 许可授予",
          "content": [
            {
              "type": "p",
              "text": "我们授予您有限的、非独占的、不可转让的、可撤销的许可，允许您根据 Apple 的 App Store 服务条款，在您拥有或控制的 Apple 品牌设备上下载并使用本应用程序，仅供个人非商业用途。"
            },
            {
              "type": "p",
              "text": "未明确授予您的所有权利均由许可方保留。"
            }
          ]
        },
        {
          "title": "2. 所有权",
          "content": [
            { "type": "p", "text": "本应用程序，包括但不限于：" },
            {
              "type": "list",
              "items": [
                "软件",
                "游戏",
                "计分系统",
                "算法",
                "视觉设计",
                "用户界面",
                "商标和徽标"
              ]
            },
            {
              "type": "p",
              "text": "归许可方所有，并受知识产权法保护。"
            },
            {
              "type": "p",
              "text": "本 EULA 不会将本应用程序或任何知识产权的所有权转让给您。"
            }
          ]
        },
        {
          "title": "3. 限制",
          "content": [
            { "type": "p", "text": "您同意不进行以下操作：" },
            {
              "type": "list",
              "items": [
                "复制、修改或创建本应用程序的衍生作品",
                "对本应用程序进行逆向工程、反编译 or 反汇编",
                "尝试访问源代码或内部 API",
                "规避技术保护或安全措施",
                "出租、租赁、出借、出售、再许可或重新分发本应用程序",
                "将本应用程序用于非法目的"
              ]
            },
            {
              "type": "p",
              "text": "任何此类尝试均违反本 EULA，并可能导致终止。"
            }
          ]
        },
        {
          "title": "4. 更新和修改",
          "content": [
            { "type": "p", "text": "我们可能会：" },
            {
              "type": "list",
              "items": [
                "修改或更新本应用程序",
                "添加或删除功能或游戏",
                "更改计分或功能",
                "随时停止本应用程序"
              ]
            },
            {
              "type": "p",
              "text": "我们要没有义务提供更新或持续的可用性。"
            }
          ]
        },
        {
          "title": "5. 终止",
          "content": [
            {
              "type": "p",
              "text": "本许可在终止前有效。"
            },
            {
              "type": "list",
              "items": [
                "您可以随时通过删除本应用程序来终止本 EULA。",
                "如果您违反任何条款，我们要可能会立即终止本 EULA。",
                "终止后，您必须停止使用本应用程序并删除所有副本。"
              ]
            }
          ]
        },
        {
          "title": "6. 免责声明",
          "content": [
            {
              "type": "p",
              "text": "本应用程序按“原样”和“可用”提供。"
            },
            {
              "type": "p",
              "text": "在法律允许的最大范围内，我们要不承担所有保证，包括但不限于："
            },
            {
              "type": "list",
              "items": [
                "适销性",
                "特定用途的适用性",
                "结果的准确性或可靠性",
                "非侵权"
              ]
            },
            {
              "type": "p",
              "text": "我们要不保证本应用程序无误、不间断或满足您的期望。"
            }
          ]
        },
        {
          "title": "7. 责任限制",
          "content": [
            { "type": "p", "text": "在法律允许的最大范围内：" },
            {
              "type": "list",
              "items": [
                "对于数据丢失、性能不准确或第三方故障，我们要不承担责任",
                "对于间接、附带或后果性损害，我们要不承担责任",
                "我们的总责任不超过您在过去 12 个月内为本应用程序支付的金额（如有）"
              ]
            }
          ]
        },
        {
          "title": "8. 无医疗或专业用途",
          "content": [
            {
              "type": "p",
              "text": "Lobe 仅供娱乐和教育目的使用。"
            },
            {
              "type": "list",
              "items": [
                "本应用程序不是医疗设备",
                "它不提供诊断、治疗或医疗建议",
                "不对认知或健康结果做出任何声明"
              ]
            },
            {
              "type": "p",
              "text": "请勿依赖本应用程序做出医疗或专业决定。"
            }
          ]
        },
        {
          "title": "9. 第三方平台 (Apple)",
          "content": [
            {
              "type": "p",
              "text": "本 EULA 是您与许可方之间的协议，而非 Apple。"
            },
            { "type": "p", "text": "Apple：" },
            {
              "type": "list",
              "items": [
                "不对本应用程序负责",
                "没有义务提供支持",
                "不对与本应用程序相关的索赔负责"
              ]
            },
            {
              "type": "p",
              "text": "如果本应用程序不符合任何适用的保证，您可以通知 Apple，Apple 可能会退还购买价格（如有），但 Apple 没有进一步的义务。"
            },
            {
              "type": "p",
              "text": "Apple 及其子公司是本 EULA 的第三方受益人，可以对您执行本协议。"
            }
          ]
        },
        {
          "title": "10. 适用法律",
          "content": [
            {
              "type": "p",
              "text": "本 EULA 受美国法律管辖，不考虑法律冲突原则。"
            }
          ]
        },
        {
          "title": "11. 可分割性",
          "content": [
            {
              "type": "p",
              "text": "如果本 EULA 的任何条款被认定为不可执行，其余条款仍然完全有效。"
            }
          ]
        },
        {
          "title": "12. 联系方式",
          "content": [{ "type": "p", "text": "关于本 EULA 的问题：" }]
        }
      ]
    },
    "privacy": {
      "title": "隐私政策",
      "lastUpdated": "2026年1月8日",
      "intro": [
        "本隐私政策描述了 Lobe (“我们”或“我们的”) 在您使用 Lobe 移动应用程序 (“App”) 时如何收集、使用、存储和保护信息。",
        "使用本应用程序即表示您同意本隐私政策中描述的信息收集和使用。"
      ],
      "sections": [
        {
          "title": "1. 我们收集的信息",
          "subsections": [
            {
              "title": "您提供的信息",
              "list": [
                "电子邮件地址",
                "姓名",
                "出生日期",
                "帐户相关信息",
                "与支持部门的沟通"
              ]
            },
            {
              "title": "自动收集的信息",
              "list": [
                "游戏性能和分数",
                "应用使用数据和会话活动",
                "设备标识符",
                "分析数据",
                "崩溃报告 (通过 Apple)"
              ],
              "note": "我们要不会故意收集 IP 地址，尽管有限的技术数据可能会由平台提供商自动处理。"
            }
          ]
        },
        {
          "title": "2. Cookie 和跟踪技术",
          "content": [
            {
              "type": "p",
              "text": "我们要可能会使用 cookie 或类似的跟踪技术来："
            },
            {
              "type": "list",
              "items": ["了解应用使用情况", "提高性能", "分析趋势"]
            },
            {
              "type": "p",
              "text": "这些技术仅用于分析和功能，不用于广告。"
            }
          ]
        },
        {
          "title": "3. 我们如何使用您的信息",
          "content": [
            { "type": "p", "text": "我们要将收集到的信息用于：" },
            {
              "type": "list",
              "items": [
                "提供和运营本应用程序",
                "跟踪游戏进度和表现",
                "改进游戏和功能",
                "监控应用稳定性和崩溃",
                "传达服务相关更新",
                "提供客户支持"
              ]
            }
          ]
        },
        {
          "title": "4. 分析和第三方服务",
          "content": [
            {
              "type": "p",
              "text": "我们要使用受信任的第三方服务提供商，包括："
            },
            {
              "type": "list",
              "items": [
                "Apple App Analytics",
                "RevenueCat",
                "Supabase (数据存储和后端基础设施)"
              ]
            },
            {
              "type": "p",
              "text": "这些提供商仅代表我们要处理数据，并受保密义务约束。"
            },
            {
              "type": "p",
              "text": "我们要不使用广告跟踪 (包括 IDFA) 并且不显示第三方广告。"
            }
          ]
        },
        {
          "title": "5. 数据所有权和汇总",
          "content": [
            {
              "type": "list",
              "items": [
                "您保留个人数据的所有权。",
                "我们要可能会汇总和匿名化数据以用于分析、产品改进或潜在研究目的。",
                "汇总数据不会识别个人用户。"
              ]
            }
          ]
        },
        {
          "title": "6. 数据共享",
          "content": [
            {
              "type": "list",
              "items": [
                "我们要不出售个人数据。",
                "我们要仅在以下情况下共享数据：",
                "与运营本应用程序所必需的服务提供商共享",
                "为了遵守法律义务",
                "为了保护 Lobe 的权利、安全或完整性"
              ]
            }
          ]
        },
        {
          "title": "7. 数据存储和保留",
          "content": [
            {
              "type": "list",
              "items": [
                "数据存储在美国。",
                "除非另有说明，否则保留个人数据。",
                "删除帐户后，个人数据将被删除，除非法律要求保留。"
              ]
            }
          ]
        },
        {
          "title": "8. 您的权利",
          "content": [
            {
              "type": "p",
              "text": "根据您所在的位置，您可能有权："
            },
            {
              "type": "list",
              "items": [
                "访问您的个人数据",
                "更正不准确的信息",
                "请求删除您的数据",
                "请求数据可移植性",
                "在适用情况下撤回同意"
              ]
            },
            {
              "type": "p",
              "text": "我们要将根据法律要求在 30 天内回复经过验证的请求。"
            },
            {
              "type": "p",
              "text": "如有请求，可通过下方列出的电子邮件联系我们。"
            }
          ]
        },
        {
          "title": "9. 儿童隐私",
          "content": [
            {
              "type": "list",
              "items": [
                "Lobe 供 13 岁及以上用户使用。",
                "我们不会故意保留 13 岁以下用户的个人数据。",
                "如果发现 13 岁以下用户的数据，我们将立即将其删除。"
              ]
            }
          ]
        },
        {
          "title": "10. 数据安全",
          "content": [
            {
              "type": "p",
              "text": "我们要实施合理的技术和组织保障措施来保护您的信息。但是，没有任何系统是完全安全的，我们无法保证绝对安全。"
            }
          ]
        },
        {
          "title": "11. 国际用户",
          "content": [
            {
              "type": "p",
              "text": "Lobe 可在全球范围内使用。如果您在美国境外访问本应用程序，即表示您同意将您的信息传输和处理到美国或我们要的服务提供商运营的其他司法管辖区。"
            },
            {
              "type": "p",
              "text": "本政策旨在遵守适用的隐私法律，包括 GDPR 和 CCPA/CPRA（如有要求）。"
            }
          ]
        },
        {
          "title": "12. 本隐私政策的变更",
          "content": [
            {
              "type": "p",
              "text": "我们要可能会不时更新本隐私政策。"
            },
            {
              "type": "p",
              "text": "重大变更将通过本应用程序或电子邮件通知。"
            }
          ]
        },
        {
          "title": "13. 联系方式",
          "content": [
            {
              "type": "p",
              "text": "如果您有关于隐私的问题、疑虑或请求："
            }
          ]
        }
      ]
    },
    "terms": {
      "title": "服务条款",
      "lastUpdated": "2026年1月8日",
      "intro": [
        "本服务条款 (“条款”) 管辖您访问和使用由位于美国特拉华州的个人 (“我们”或“我们的”) 运营的 Lobe 移动应用程序 (“App”)。",
        "下载、访问或使用 Lobe 即表示您同意受本条款的约束。如果您不同意，请勿使用本应用程序。"
      ],
      "sections": [
        {
          "title": "1. 资格",
          "content": [
            {
              "type": "p",
              "text": "Lobe 供 13 岁及以上用户使用。"
            },
            {
              "type": "p",
              "text": "使用本应用程序即表示您声明您符合此年龄要求。"
            },
            {
              "type": "p",
              "text": "如果您未满 18 岁，即表示您已获得父母或法定监护人的许可。"
            }
          ]
        },
        {
          "title": "2. 帐户注册和访问",
          "content": [
            {
              "type": "list",
              "items": [
                "访问某些功能可能需要帐户。",
                "您有责任维护帐户凭据的机密性。",
                "您可以随时使用应用内帐户删除功能删除您的帐户。",
                "我们要保留自行决定暂停或终止帐户的权利，包括违反本条款或滥用本应用程序的情况。"
              ]
            }
          ]
        },
        {
          "title": "3. 订阅、计费和付款",
          "subsections": [
            {
              "title": "订阅模式",
              "list": [
                "Lobe 是一款付费应用程序。",
                "订阅通过 Apple App Store 处理，计费通过 RevenueCat 管理。",
                "可用计划可能包括每周、每月、每年或终身订阅。"
              ]
            },
            {
              "title": "免费试用和自动续订",
              "list": [
                "我们要可能会自行决定提供免费试用。",
                "除非在当前计费周期结束前至少 24 小时取消，否则订阅会自动续订。",
                "订阅管理和取消通过您的 Apple ID 设置处理。"
              ]
            },
            {
              "title": "退款",
              "list": [
                "在合理情况下，我们要可能会自行决定提供超出 Apple 标准政策的退款。",
                "Apple 控制最终后的退款资格和处理。"
              ]
            },
            {
              "title": "价格变动",
              "list": [
                "定价和订阅条款可能随时更改。",
                "更改在下一个续订周期之前不会影响有效订阅。"
              ]
            }
          ]
        },
        {
          "title": "4. 可接受的使用",
          "content": [
            { "type": "p", "text": "您同意不进行以下操作：" },
            {
              "type": "list",
              "items": [
                "对 Lobe 的源代码进行逆向工程、反编译或尝试访问",
                "规避安全功能或技术保护",
                "使用自动化系统 (机器人、爬虫) 访问本应用程序",
                "干扰性能跟踪、评分或分析系统",
                "以违反适用法律的方式滥用本应用程序"
              ]
            }
          ]
        },
        {
          "title": "5. 知识产权",
          "content": [
            {
              "type": "list",
              "items": [
                "所有游戏、计分系统、算法、UI/UX 和底层技术均为我们要所有。",
                "您被授予有限的、非独占的、不可转让的许可，仅供个人非商业用途使用本应用程序。",
                "未经许可，您不得复制、重新分发或利用应用内容。"
              ]
            }
          ],
          "subsections": [
            {
              "title": "反馈",
              "content": "您提供的任何反馈或建议，我们要均可不受限制或无需补偿地使用。"
            }
          ]
        },
        {
          "title": "6. 用户数据和隐私",
          "content": [
            {
              "type": "p",
              "text": "您对 Lobe 的使用也受我们的隐私政策的约束。"
            }
          ],
          "subsections": [
            {
              "title": "收集的数据",
              "content": "我们要可能收集：",
              "list": [
                "电子邮件地址",
                "姓名",
                "生日",
                "游戏性能和分数",
                "设备标识符",
                "使用分析"
              ]
            },
            {
              "title": "数据所有权",
              "list": [
                "您保留个人数据的所有权。",
                "除另有说明外，我们要可能会存储数据。",
                "我们要可能会汇总和匿名化数据以用于分析和产品改进。"
              ]
            },
            {
              "title": "第三方服务",
              "list": [
                "数据可能由 Supabase 和分析工具等受信任的服务提供商处理。",
                "我们要不出售个人数据。"
              ]
            }
          ]
        },
        {
          "title": "7. 数据共享和导出",
          "content": [
            {
              "type": "list",
              "items": [
                "您可以自行决定公开发布您的结果。",
                "您可能会请求导出数据，这需要经过验证。"
              ]
            }
          ]
        },
        {
          "title": "8. 教育和非医疗免责声明",
          "content": [
            {
              "type": "list",
              "items": [
                "Lobe 仅供娱乐和教育目的使用。",
                "Lobe 不是医疗设备",
                "它不提供诊断、治疗或医疗建议",
                "不对认知改善、心理健康结果或临床有效性做出任何声明",
                "请勿将 Lobe 用作专业医疗建议的替代品"
              ]
            }
          ]
        },
        {
          "title": "9. 可用性和修改",
          "content": [
            { "type": "p", "text": "我们要保留以下权利：" },
            {
              "type": "list",
              "items": [
                "修改功能",
                "删除游戏",
                "调整计分模型",
                "随时停止本应用程序"
              ]
            },
            {
              "type": "p",
              "text": "我们要不保证不间断或无错误的可用性。"
            }
          ]
        },
        {
          "title": "10. 终止",
          "content": [
            {
              "type": "list",
              "items": [
                "您可以随时停止使用 Lobe。",
                "删除帐户或终止后，用户数据将被删除，除非法律要求保留。",
                "除法律要求的条款外，无任何条款在终止后继续有效。"
              ]
            }
          ]
        },
        {
          "title": "11. 免责声明",
          "content": [
            {
              "type": "p",
              "text": "Lobe 按“原样”和“可用”提供。"
            },
            {
              "type": "p",
              "text": "我们要不承担所有保证，包括但不限于："
            },
            {
              "type": "list",
              "items": [
                "性能指标的准确性",
                "数据可靠性或完整性",
                "特定用途的适用性",
                "可用性或正常运行时间"
              ]
            }
          ]
        },
        {
          "title": "12. 责任限制",
          "content": [
            { "type": "p", "text": "在法律允许的最大范围内：" },
            {
              "type": "list",
              "items": [
                "对于数据丢失、性能不准确或第三方故障，我们要不承担责任",
                "对于滥用本应用程序，我们要不负责",
                "我们的总责任仅限于您在过去 12 个月内支付的金额（如有）"
              ]
            }
          ]
        },
        {
          "title": "13. 赔偿",
          "content": [
            {
              "type": "p",
              "text": "您同意就因以下原因引起的索赔赔偿我们并使我们免受损害："
            },
            {
              "type": "list",
              "items": ["您滥用本应用程序", "违反本条款", "违反适用法律"]
            }
          ]
        },
        {
          "title": "14. 适用法律和争议",
          "content": [
            {
              "type": "list",
              "items": [
                "本条款受美国法律管辖。",
                "争议可在小额索赔法院提出（如适用）。",
                "您放弃参与集体诉讼 or 集体仲裁的权利。"
              ]
            }
          ]
        },
        {
          "title": "15. 通信",
          "content": [
            {
              "type": "list",
              "items": [
                "我们要可能会发送与产品更新、服务通知和促销相关的电子邮件。",
                "您可以随时选择退出促销电子邮件。"
              ]
            }
          ]
        },
        {
          "title": "16. 国际用户",
          "content": [
            {
              "type": "list",
              "items": ["Lobe 供美国境外用户使用。", "您负责遵守当地法律。"]
            }
          ]
        },
        {
          "title": "17. 联系方式",
          "content": [
            {
              "type": "p",
              "text": "有关本条款的法律通知或问题："
            }
          ]
        }
      ]
    }
  }
}
